gw_soilpy.py
gw_soilpy-1.0.0.dist-info/METADATA
gw_soilpy-1.0.0.dist-info/WHEEL
gw_soilpy-1.0.0.dist-info/entry_points.txt
gw_soilpy-1.0.0.dist-info/top_level.txt
gw_soilpy-1.0.0.dist-info/RECORD
